setup.py
bot_chucky/__init__.py
bot_chucky/bot.py
bot_chucky/constants.py
bot_chucky/errors.py
bot_chucky/helpers.py
bot_chucky/utils.py
bot_chucky.egg-info/PKG-INFO
bot_chucky.egg-info/SOURCES.txt
bot_chucky.egg-info/dependency_links.txt
bot_chucky.egg-info/requires.txt
bot_chucky.egg-info/top_level.txt