Metadata-Version: 1.1
Name: bot-chucky
Version: 0.1.1
Summary: Python bot which able to work with messenger of facebook
Home-page: https://github.com/MichaelYusko/Bot-Chucky
Author: Frozen Monkey
Author-email: freshjelly12@yahoo.com
License: MIT
Platform: UNKNOWN
Classifier: Development Status :: 3 - Alpha
Classifier: Environment :: Web Environment
Classifier: Programming Language :: Python :: 3.6
Classifier: License :: OSI Approved :: MIT License
